<DOMSymbolItem xmlns:xsi="http://www.w3.org/2001/XMLSchema-instance" xmlns="http://ns.adobe.com/xfl/2008/" name="  Course Clips/ 1 - Bob-omb Battlefield/  Areas 1-3 &amp; 1-5/1-3 Back GFX" itemID="45a5ba1e-00000250" linkageExportForAS="true" linkageExportInFirstFrame="false" linkageIdentifier="1-3BackGFX" lastModified="1239676699" lastUniqueIdentifier="203">
  <timeline>
    <DOMTimeline name="1-3 Back GFX">
      <layers>
        <DOMLayer name="Layer 2" color="#9933CC">
          <frames>
            <DOMFrame index="0" duration="3" keyMode="9728">
              <elements/>
            </DOMFrame>
            <DOMFrame index="3" keyMode="9728">
              <Actionscript>
                <script><![CDATA[stop();
_root.warpframe = false;
onEnterFrame = function () {
	if (this.warp1.hitTest(_root.Course.Char.charClip.feet)) {
		_root.Course.Char.attack = true;
		_root.Course.Char.xspeed = 0;
		_root.Course.Char.yspeed = 0;
		_root.Course.Char.attackFrame = "none";
		warp = true;
		warpnum = 1;
	}
	if (this.warp2.hitTest(_root.Course.Char.charClip.feet)) {
		_root.Course.Char.attack = true;
		_root.Course.Char.xspeed = 0;
		_root.Course.Char.yspeed = 0;
		_root.Course.Char.attackFrame = "none";
		warp = true;
		warpnum = 2;
	}
	if (warp == true && _root.warpframe == false) {
		if (warpnum == 1) {
			_root.attachMovie("downtransition", "lefttransition"+_root.getNextHighestDepth(), _root.getNextHighestDepth(), {_x:_root.screensizeX/2, _y:_root.screensizeY/2});
		}
		if (warpnum == 2) {
			_root.attachMovie("righttransition", "righttransition"+_root.getNextHighestDepth(), _root.getNextHighestDepth(), {_x:_root.screensizeX/2, _y:_root.screensizeY/2});
		}
		warp = false;
	}
	if (_root.warpframe == true) {
		if (warpnum == 1) {
			_root.changecourse("downtransition2", "1-1", 2000+(_root.Course.Char._x-_root.Course.CamEdge._x), -100, 2000+(_root.Course.Char._x-_root.Course.CamEdge._x), -300);
		}
		if (warpnum == 2) {
			_root.changecourse("righttransition2", "1-2", 0, -200, 0, -320);
		}
		//_root.warpframe = false;                             
	}
};
]]></script>
              </Actionscript>
              <elements/>
            </DOMFrame>
          </frames>
        </DOMLayer>
        <DOMLayer name="Layer 3" color="#FFFF4F" outline="true" current="true" isSelected="true" useOutlineView="true">
          <frames>
            <DOMFrame index="0" keyMode="9728">
              <elements/>
            </DOMFrame>
            <DOMFrame index="1" duration="2" keyMode="9728">
              <elements>
                <DOMSymbolInstance libraryItemName=" Xtra/Blank Movieclip">
                  <matrix>
                    <Matrix a="37.7353210449219" d="22.7369689941406" tx="-1239" ty="37.4"/>
                  </matrix>
                  <transformationPoint>
                    <Point/>
                  </transformationPoint>
                  <Actionscript>
                    <script><![CDATA[onClipEvent (load) {
	_visible = false;
}
onClipEvent (enterFrame) {
	if (this.hitTest(_root.Course.Char.charClip.body)) {
		_root.Course.Char.xspeed = Math.random()*4-2;
		_root.Course.Char.yspeed = -14;
	}
}
]]></script>
                  </Actionscript>
                </DOMSymbolInstance>
                <DOMSymbolInstance libraryItemName=" Xtra/Blank Movieclip">
                  <matrix>
                    <Matrix a="15.6209259033203" d="30.5096588134766" tx="-2521.4" ty="142.1"/>
                  </matrix>
                  <transformationPoint>
                    <Point/>
                  </transformationPoint>
                  <Actionscript>
                    <script><![CDATA[onClipEvent (load) {
	_visible = false;
}
onClipEvent (enterFrame) {
	if (this.hitTest(_root.Course.Char.charClip.body)) {
		_root.Course.Char._x += 200;
	}
}
]]></script>
                  </Actionscript>
                </DOMSymbolInstance>
              </elements>
            </DOMFrame>
            <DOMFrame index="3" keyMode="9728">
              <elements>
                <DOMSymbolInstance libraryItemName=" Xtra/Blank Movieclip">
                  <matrix>
                    <Matrix a="32.0748901367188" d="62.4983978271484" tx="-378.5" ty="-1022.3"/>
                  </matrix>
                  <transformationPoint>
                    <Point/>
                  </transformationPoint>
                  <Actionscript>
                    <script><![CDATA[onClipEvent (load) {
	_visible = false;
}
onClipEvent (enterFrame) {
	if (_root.PauseGame == false && _root.playpause == false) {
		if (this.hitTest(_root.Course.Char.charClip.body)) {
			_root.Course.Char.xspeed = _root.groundFriction(_root.Course.Char.xspeed, 0.05, 1.05);
			_root.Course.Char.xspeed -= 1;
			_root.Course.Char.yspeed = _root.groundFriction(_root.Course.Char.yspeed, 0.07, 1.01);
			_root.Course.Char.yspeed -= 0.5;
		}
	}
}
]]></script>
                  </Actionscript>
                </DOMSymbolInstance>
                <DOMSymbolInstance libraryItemName=" Xtra/Blank Movieclip">
                  <matrix>
                    <Matrix a="3.77366638183594" d="62.4983978271484" tx="-1190.4" ty="-1022.3"/>
                  </matrix>
                  <transformationPoint>
                    <Point/>
                  </transformationPoint>
                  <Actionscript>
                    <script><![CDATA[onClipEvent (load) {
	_visible = false;
}
onClipEvent (enterFrame) {
	if (_root.PauseGame == false && _root.playpause == false) {
		if (this.hitTest(_root.Course.Char.charClip.body)) {
			_root.Course.Char.xspeed = _root.groundFriction(_root.Course.Char.xspeed, 0.03, 1.03);
			_root.Course.Char.xspeed -= 0.7;
			_root.Course.Char.yspeed = _root.groundFriction(_root.Course.Char.yspeed, 0.03, 1.01);
			_root.Course.Char.yspeed -= 1.3
		}
	}
}
]]></script>
                  </Actionscript>
                </DOMSymbolInstance>
                <DOMSymbolInstance libraryItemName=" Xtra/Blank Movieclip">
                  <matrix>
                    <Matrix a="5.81004333496094" d="12.4997863769531" tx="-1410.4" ty="-1422.3"/>
                  </matrix>
                  <transformationPoint>
                    <Point/>
                  </transformationPoint>
                  <Actionscript>
                    <script><![CDATA[onClipEvent (load) {
	_visible = false;
}
onClipEvent (enterFrame) {
	if (_root.PauseGame == false && _root.playpause == false) {
		if (this.hitTest(_root.Course.Char.charClip.body)) {
			_root.Course.Char.xspeed = _root.groundFriction(_root.Course.Char.xspeed, 0.03, 1.02);
			_root.Course.Char.xspeed -= 0.5;
		}
	}
}
]]></script>
                  </Actionscript>
                </DOMSymbolInstance>
                <DOMSymbolInstance libraryItemName=" Xtra/Blank Movieclip">
                  <matrix>
                    <Matrix a="-8.70356750488281" d="-22.1874389648438" tx="-2082.35" ty="-290.6"/>
                  </matrix>
                  <transformationPoint>
                    <Point/>
                  </transformationPoint>
                  <Actionscript>
                    <script><![CDATA[onClipEvent (load) {
	_visible = false;
}
/*
onEnterFrame = function () {
_root.CamYchange = 35
};*/
onClipEvent (enterFrame) {
	if (this.hitTest(_root.Course.Char.charClip.body) && _root._quality !== "LOW" && _root._quality !== "MEDIUM") {
		if (_root.PauseGame == false && _root.playpause == false) {
			//_root.Course.Char.yspeed = _root.groundFriction(_root.Course.Char.yspeed, 0.015, 1.001);
			if (savezoom == undefined) {
				savezoom = _root.CameraZoom;
			}
			if (_root.CameraZoom>75) {
				_root.CameraZoom -= 1;
			}
		}
	} else {
		if (savezoom !== undefined) {
			if (_root.CameraZoom<savezoom) {
				_root.CameraZoom += 1;
			} else {
				savezoom = undefined;
			}
		}
	}
}
]]></script>
                  </Actionscript>
                </DOMSymbolInstance>
                <DOMSymbolInstance libraryItemName=" Xtra/Blank Movieclip">
                  <matrix>
                    <Matrix a="-3.74392700195313" d="-7.99327087402344" tx="-355.75" ty="-22.5"/>
                  </matrix>
                  <transformationPoint>
                    <Point/>
                  </transformationPoint>
                  <Actionscript>
                    <script><![CDATA[onClipEvent (load) {
	_visible = false;
}
onClipEvent (enterFrame) {
	if (this.hitTest(_root.Course.Char.charClip.body)&& _root._quality !== "LOW" && _root._quality !== "MEDIUM") {
		if (_root.PauseGame == false && _root.playpause == false) {
			//_root.Course.Char.yspeed = _root.groundFriction(_root.Course.Char.yspeed, 0.015, 1.001);
			if (savezoom == undefined) {
				savezoom = _root.CameraZoom;
			}
			if (_root.CameraZoom>85) {
				_root.CameraZoom -= 1;
			}
		}
	} else {
		if (savezoom !== undefined) {
			if (_root.CameraZoom<savezoom) {
				_root.CameraZoom += 1;
			} else {
				savezoom = undefined;
			}
		}
	}
}
]]></script>
                  </Actionscript>
                </DOMSymbolInstance>
                <DOMSymbolInstance libraryItemName=" Xtra/Blank Movieclip">
                  <matrix>
                    <Matrix a="-26.0222778320313" d="-33.2766723632813" tx="-2099.55" ty="-1237.55"/>
                  </matrix>
                  <transformationPoint>
                    <Point/>
                  </transformationPoint>
                  <Actionscript>
                    <script><![CDATA[onClipEvent (load) {
	_visible = false;
}
onClipEvent (enterFrame) {
	if (this.hitTest(_root.Course.Char.charClip.body) && _root._quality !== "LOW" && _root._quality !== "MEDIUM") {
		if (_root.PauseGame == false && _root.playpause == false) {
			//_root.Course.Char.yspeed = _root.groundFriction(_root.Course.Char.yspeed, 0.015, 1.001);
			if (savezoom == undefined) {
				savezoom = _root.CameraZoom;
			}
			if (_root.CameraZoom>50) {
				_root.CameraZoom -= 1;
			}
		}
	} else {
		if (savezoom !== undefined) {
			if (_root.CameraZoom<savezoom) {
				_root.CameraZoom += 1;
			} else {
				savezoom = undefined;
			}
		}
	}
}
]]></script>
                  </Actionscript>
                </DOMSymbolInstance>
                <DOMSymbolInstance libraryItemName="  Course Items-PL/ In-course Items/ Other/Camera Control Box" selected="true">
                  <matrix>
                    <Matrix a="2.49996948242188" d="1.55999755859375" tx="-2384.9" ty="-792"/>
                  </matrix>
                  <transformationPoint>
                    <Point/>
                  </transformationPoint>
                  <Actionscript>
                    <script><![CDATA[onClipEvent (load) {
	t = "Y";
	amount = -50
	speed = 10
}
]]></script>
                  </Actionscript>
                </DOMSymbolInstance>
              </elements>
            </DOMFrame>
          </frames>
        </DOMLayer>
        <DOMLayer name="Layer 1" color="#4FFF4F">
          <frames>
            <DOMFrame index="0" duration="4" keyMode="9728">
              <elements>
                <DOMSymbolInstance libraryItemName=" Xtra/Blank Movieclip" name="warp1">
                  <matrix>
                    <Matrix a="47.9342651367188" d="6.24969482421875" tx="-1137" ty="193.4"/>
                  </matrix>
                  <transformationPoint>
                    <Point/>
                  </transformationPoint>
                  <Actionscript>
                    <script><![CDATA[onClipEvent (load) {
	_visible = false;
}
]]></script>
                  </Actionscript>
                </DOMSymbolInstance>
                <DOMSymbolInstance libraryItemName="  Course Items-PL/ In-course Items/ Collectables/ Coin: Yellow Folder/Gold Coin Code">
                  <matrix>
                    <Matrix tx="-2081.35" ty="-566.95"/>
                  </matrix>
                  <transformationPoint>
                    <Point/>
                  </transformationPoint>
                </DOMSymbolInstance>
                <DOMSymbolInstance libraryItemName="  Course Items-PL/ In-course Items/ Collectables/ Coin: Yellow Folder/Gold Coin Code">
                  <matrix>
                    <Matrix tx="-2133.55" ty="-566.95"/>
                  </matrix>
                  <transformationPoint>
                    <Point/>
                  </transformationPoint>
                </DOMSymbolInstance>
                <DOMSymbolInstance libraryItemName="   Enemies/Normal/ G-Z/ Goonie/Goonie Code">
                  <matrix>
                    <Matrix tx="-901" ty="-52.95"/>
                  </matrix>
                  <transformationPoint>
                    <Point/>
                  </transformationPoint>
                  <Actionscript>
                    <script><![CDATA[onClipEvent (load) {
	_xscale = 100;
}
]]></script>
                  </Actionscript>
                </DOMSymbolInstance>
                <DOMSymbolInstance libraryItemName="  Course Items-PL/ In-course Items/ Collectables/ Coin: Red Folder/Red Coin Code">
                  <matrix>
                    <Matrix tx="-2014.35" ty="-213"/>
                  </matrix>
                  <transformationPoint>
                    <Point/>
                  </transformationPoint>
                </DOMSymbolInstance>
                <DOMSymbolInstance libraryItemName="  Course Items-PL/ In-course Items/ Collectables/ Coin: Yellow Folder/Gold Coin Code">
                  <matrix>
                    <Matrix tx="-411.2" ty="-11.5"/>
                  </matrix>
                  <transformationPoint>
                    <Point/>
                  </transformationPoint>
                </DOMSymbolInstance>
                <DOMSymbolInstance libraryItemName="  Course Items-PL/ In-course Items/ Collectables/ Coin: Yellow Folder/Gold Coin Code">
                  <matrix>
                    <Matrix tx="-313.55" ty="-13.5"/>
                  </matrix>
                  <transformationPoint>
                    <Point/>
                  </transformationPoint>
                </DOMSymbolInstance>
                <DOMBitmapInstance libraryItemName="  Course Items-PL/ Decoration/ Vegetation/ Regular/Tree 64">
                  <matrix>
                    <Matrix tx="-1415.75" ty="-1136.6"/>
                  </matrix>
                </DOMBitmapInstance>
                <DOMSymbolInstance libraryItemName="  Course Items-PL/ In-course Items/ Collectables/ Starry Stuff/Shine Sprite Clip">
                  <matrix>
                    <Matrix tx="-1308.85" ty="-1150"/>
                  </matrix>
                  <transformationPoint>
                    <Point/>
                  </transformationPoint>
                  <Actionscript>
                    <script><![CDATA[onClipEvent (load) {
	starnum = 2;
}
]]></script>
                  </Actionscript>
                </DOMSymbolInstance>
                <DOMSymbolInstance libraryItemName=" Xtra/Blank Movieclip" name="warp2">
                  <matrix>
                    <Matrix a="7.14115905761719" d="31.8188323974609" tx="312.4" ty="-78.75"/>
                  </matrix>
                  <transformationPoint>
                    <Point/>
                  </transformationPoint>
                  <Actionscript>
                    <script><![CDATA[onClipEvent (load) {
	_visible = false;
}
]]></script>
                  </Actionscript>
                </DOMSymbolInstance>
                <DOMSymbolInstance libraryItemName="  Course Items-PL/ In-course Items/ Collectables/ Coin: Yellow Folder/Gold Coin Code">
                  <matrix>
                    <Matrix tx="-96.55" ty="14.3"/>
                  </matrix>
                  <transformationPoint>
                    <Point/>
                  </transformationPoint>
                </DOMSymbolInstance>
                <DOMSymbolInstance libraryItemName="  Course Items-PL/ In-course Items/ Collectables/ Coin: Yellow Folder/Gold Coin Code">
                  <matrix>
                    <Matrix tx="-66.55" ty="14.3"/>
                  </matrix>
                  <transformationPoint>
                    <Point/>
                  </transformationPoint>
                </DOMSymbolInstance>
                <DOMBitmapInstance libraryItemName="  Course Items-PL/ Decoration/ Signs &amp; Fences/YI Arrow">
                  <matrix>
                    <Matrix a="0" b="1" c="-1" d="0" tx="59.45" ty="-16.05"/>
                  </matrix>
                </DOMBitmapInstance>
                <DOMBitmapInstance libraryItemName="  Course Items-PL/ Decoration/ Signs &amp; Fences/YI Arrow">
                  <matrix>
                    <Matrix a="1.52587890625e-005" b="-1" c="1" d="1.52587890625e-005" tx="-822.4" ty="-15.25"/>
                  </matrix>
                </DOMBitmapInstance>
                <DOMSymbolInstance libraryItemName="  Course Items-PL/ In-course Items/ Collectables/ Coin: Red Folder/Red Coin Code">
                  <matrix>
                    <Matrix tx="-359.5" ty="-148.05"/>
                  </matrix>
                  <transformationPoint>
                    <Point/>
                  </transformationPoint>
                </DOMSymbolInstance>
                <DOMBitmapInstance libraryItemName="  Course Items-PL/ Decoration/ Vegetation/ Regular/Tree 64">
                  <matrix>
                    <Matrix tx="-2377.35" ty="-217.95"/>
                  </matrix>
                </DOMBitmapInstance>
                <DOMSymbolInstance libraryItemName="      Char/  Fludd CLIPS/Rocket Nozzle Box Clip">
                  <matrix>
                    <Matrix tx="-2376.25" ty="-188.5"/>
                  </matrix>
                  <transformationPoint>
                    <Point/>
                  </transformationPoint>
                </DOMSymbolInstance>
                <DOMSymbolInstance libraryItemName="  Course Items-PL/ In-course Items/ Collectables/ Coin: Yellow Folder/Gold Coin Code">
                  <matrix>
                    <Matrix tx="-2373.05" ty="-328.1"/>
                  </matrix>
                  <transformationPoint>
                    <Point/>
                  </transformationPoint>
                </DOMSymbolInstance>
                <DOMSymbolInstance libraryItemName="  Course Items-PL/ In-course Items/ Collectables/ Coin: Yellow Folder/Gold Coin Code">
                  <matrix>
                    <Matrix tx="-2373.05" ty="-388.1"/>
                  </matrix>
                  <transformationPoint>
                    <Point/>
                  </transformationPoint>
                </DOMSymbolInstance>
                <DOMSymbolInstance libraryItemName="  Course Items-PL/ In-course Items/ Collectables/ Coin: Yellow Folder/Gold Coin Code">
                  <matrix>
                    <Matrix tx="-2373.05" ty="-448.1"/>
                  </matrix>
                  <transformationPoint>
                    <Point/>
                  </transformationPoint>
                </DOMSymbolInstance>
                <DOMSymbolInstance libraryItemName="  Course Items-PL/ In-course Items/ Collectables/ Coin: Blue Folder/Blue Coin Code">
                  <matrix>
                    <Matrix tx="-2373.05" ty="-537.95"/>
                  </matrix>
                  <transformationPoint>
                    <Point y="-1"/>
                  </transformationPoint>
                </DOMSymbolInstance>
                <DOMSymbolInstance libraryItemName="  Course Items-PL/ Various Platforms/ Common Coded PL/ Green PL/Moving Green Platform">
                  <matrix>
                    <Matrix tx="-1809.2" ty="-57.5"/>
                  </matrix>
                  <transformationPoint>
                    <Point/>
                  </transformationPoint>
                  <Actionscript>
                    <script><![CDATA[onClipEvent (load) {
	DirectionX = "Left";
	DirectionY = "Up";
	distanceX = 45;
	distanceY = 45;
	accelX = 0.5;
	accelY = 0.5;
	speedX = 3;
	speedY = 3;
}
]]></script>
                  </Actionscript>
                </DOMSymbolInstance>
                <DOMSymbolInstance libraryItemName="  Course Items-PL/ In-course Items/ Collectables/ Coin: Yellow Folder/Gold Coin Code">
                  <matrix>
                    <Matrix tx="-1809.45" ty="-81"/>
                  </matrix>
                  <transformationPoint>
                    <Point/>
                  </transformationPoint>
                </DOMSymbolInstance>
                <DOMSymbolInstance libraryItemName="  Course Items-PL/ In-course Items/ Collectables/ Coin: Yellow Folder/Gold Coin Code">
                  <matrix>
                    <Matrix tx="-1849.45" ty="-121"/>
                  </matrix>
                  <transformationPoint>
                    <Point/>
                  </transformationPoint>
                </DOMSymbolInstance>
                <DOMSymbolInstance libraryItemName="  Course Items-PL/ In-course Items/ Collectables/ Coin: Yellow Folder/Gold Coin Code">
                  <matrix>
                    <Matrix tx="-1889.45" ty="-161"/>
                  </matrix>
                  <transformationPoint>
                    <Point/>
                  </transformationPoint>
                </DOMSymbolInstance>
                <DOMSymbolInstance libraryItemName="  Course Items-PL/ Various Platforms/ Coded Wooden PL/Tipping Log">
                  <matrix>
                    <Matrix tx="-2118.2" ty="-183.95"/>
                  </matrix>
                  <transformationPoint>
                    <Point y="-6"/>
                  </transformationPoint>
                </DOMSymbolInstance>
                <DOMSymbolInstance libraryItemName="  Course Items-PL/ In-course Items/ Collectables/ Coin: Yellow Folder/Gold Coin Code">
                  <matrix>
                    <Matrix tx="-1929.45" ty="-201"/>
                  </matrix>
                  <transformationPoint>
                    <Point/>
                  </transformationPoint>
                </DOMSymbolInstance>
                <DOMSymbolInstance libraryItemName="  Course Items-PL/ In-course Items/ Collectables/ Coin: Yellow Folder/Gold Coin Code">
                  <matrix>
                    <Matrix tx="-2217.35" ty="-246"/>
                  </matrix>
                  <transformationPoint>
                    <Point/>
                  </transformationPoint>
                </DOMSymbolInstance>
                <DOMSymbolInstance libraryItemName="  Course Items-PL/ In-course Items/ Collectables/ Coin: Yellow Folder/Gold Coin Code">
                  <matrix>
                    <Matrix tx="-2187.35" ty="-276"/>
                  </matrix>
                  <transformationPoint>
                    <Point/>
                  </transformationPoint>
                </DOMSymbolInstance>
                <DOMSymbolInstance libraryItemName="  Course Items-PL/ In-course Items/ Collectables/ Coin: Yellow Folder/Gold Coin Code">
                  <matrix>
                    <Matrix tx="-2157.35" ty="-306"/>
                  </matrix>
                  <transformationPoint>
                    <Point/>
                  </transformationPoint>
                </DOMSymbolInstance>
                <DOMSymbolInstance libraryItemName="  Course Items-PL/ In-course Items/ Collectables/ Coin: Yellow Folder/Gold Coin Code">
                  <matrix>
                    <Matrix tx="-2127.35" ty="-336"/>
                  </matrix>
                  <transformationPoint>
                    <Point/>
                  </transformationPoint>
                </DOMSymbolInstance>
                <DOMSymbolInstance libraryItemName="  Course Items-PL/ In-course Items/ Collectables/ Coin: Yellow Folder/Gold Coin Code">
                  <matrix>
                    <Matrix tx="-2097.35" ty="-366"/>
                  </matrix>
                  <transformationPoint>
                    <Point/>
                  </transformationPoint>
                </DOMSymbolInstance>
                <DOMSymbolInstance libraryItemName="  Course Items-PL/ In-course Items/ Collectables/ Coin: Yellow Folder/Gold Coin Code">
                  <matrix>
                    <Matrix tx="-2067.35" ty="-396"/>
                  </matrix>
                  <transformationPoint>
                    <Point/>
                  </transformationPoint>
                </DOMSymbolInstance>
                <DOMSymbolInstance libraryItemName="  Course Items-PL/ Various Platforms/ Common Coded PL/ Green PL/Moving Green Platform">
                  <matrix>
                    <Matrix tx="-2023.35" ty="-402"/>
                  </matrix>
                  <transformationPoint>
                    <Point/>
                  </transformationPoint>
                  <Actionscript>
                    <script><![CDATA[onClipEvent (load) {
	DirectionX = "Left";
	DirectionY = "Up";
	distanceX = 0;
	distanceY = 50;
	accelX = 0;
	accelY = 0.5;
	speedX = 0;
	speedY = 3;
}
]]></script>
                  </Actionscript>
                </DOMSymbolInstance>
                <DOMSymbolInstance libraryItemName="  Course Items-PL/ In-course Items/ Collectables/ Coin: Yellow Folder/Gold Coin Code">
                  <matrix>
                    <Matrix tx="-2023.4" ty="-426"/>
                  </matrix>
                  <transformationPoint>
                    <Point/>
                  </transformationPoint>
                </DOMSymbolInstance>
                <DOMSymbolInstance libraryItemName="  Course Items-PL/ In-course Items/ Collectables/ Coin: Yellow Folder/Gold Coin Code">
                  <matrix>
                    <Matrix tx="-2023.4" ty="-476"/>
                  </matrix>
                  <transformationPoint>
                    <Point/>
                  </transformationPoint>
                </DOMSymbolInstance>
                <DOMSymbolInstance libraryItemName="  Course Items-PL/ In-course Items/ Collectables/ Coin: Yellow Folder/Gold Coin Code">
                  <matrix>
                    <Matrix tx="-2023.4" ty="-526"/>
                  </matrix>
                  <transformationPoint>
                    <Point/>
                  </transformationPoint>
                </DOMSymbolInstance>
                <DOMSymbolInstance libraryItemName="  Course Items-PL/ Various Platforms/ Coded Wooden PL/Tipping Log">
                  <matrix>
                    <Matrix tx="-2105.4" ty="-538"/>
                  </matrix>
                  <transformationPoint>
                    <Point y="-6"/>
                  </transformationPoint>
                </DOMSymbolInstance>
                <DOMSymbolInstance libraryItemName="  Course Items-PL/ Various Platforms/ Common Coded PL/ Green PL/Moving Green Platform">
                  <matrix>
                    <Matrix tx="-2272.9" ty="-621"/>
                  </matrix>
                  <transformationPoint>
                    <Point/>
                  </transformationPoint>
                  <Actionscript>
                    <script><![CDATA[onClipEvent (load) {
	DirectionX = "Left";
	DirectionY = "Up";
	distanceX = 0;
	distanceY = 50;
	accelX = 0;
	accelY = 0.5;
	speedX = 0;
	speedY = 3;
}
]]></script>
                  </Actionscript>
                </DOMSymbolInstance>
                <DOMSymbolInstance libraryItemName="  Course Items-PL/ In-course Items/ Collectables/ Coin: Yellow Folder/Gold Coin Code">
                  <matrix>
                    <Matrix tx="-2274.4" ty="-645"/>
                  </matrix>
                  <transformationPoint>
                    <Point/>
                  </transformationPoint>
                </DOMSymbolInstance>
                <DOMSymbolInstance libraryItemName="  Course Items-PL/ In-course Items/ Collectables/ Coin: Yellow Folder/Gold Coin Code">
                  <matrix>
                    <Matrix tx="-2274.4" ty="-695"/>
                  </matrix>
                  <transformationPoint>
                    <Point/>
                  </transformationPoint>
                </DOMSymbolInstance>
                <DOMSymbolInstance libraryItemName="  Course Items-PL/ In-course Items/ Collectables/ Coin: Yellow Folder/Gold Coin Code">
                  <matrix>
                    <Matrix tx="-2274.4" ty="-745"/>
                  </matrix>
                  <transformationPoint>
                    <Point/>
                  </transformationPoint>
                </DOMSymbolInstance>
                <DOMSymbolInstance libraryItemName="  Course Items-PL/ Various Platforms/ Coded Wooden PL/Tipping Log">
                  <matrix>
                    <Matrix tx="-2402.2" ty="-724.05"/>
                  </matrix>
                  <transformationPoint>
                    <Point y="-6"/>
                  </transformationPoint>
                  <Actionscript>
                    <script><![CDATA[onClipEvent (load) {
	scale = 2;
}
]]></script>
                  </Actionscript>
                </DOMSymbolInstance>
                <DOMBitmapInstance libraryItemName="  Course Items-PL/ Decoration/ Signs &amp; Fences/YI Arrow">
                  <matrix>
                    <Matrix a="0.258834838867188" b="-0.965911865234375" c="0.965927124023438" d="0.258834838867188" tx="-1458.25" ty="-0.6"/>
                  </matrix>
                </DOMBitmapInstance>
                <DOMBitmapInstance libraryItemName="  Course Items-PL/ Decoration/ Signs &amp; Fences/YI Arrow">
                  <matrix>
                    <Matrix a="-0.812942504882813" b="-0.578292846679688" c="0.578292846679688" d="-0.812942504882813" tx="-2680.2" ty="-805.85"/>
                  </matrix>
                </DOMBitmapInstance>
                <DOMGroup>
                  <matrix>
                    <Matrix tx="-90"/>
                  </matrix>
                  <members>
                    <DOMShape>
                      <matrix>
                        <Matrix tx="-90"/>
                      </matrix>
                      <fills>
                        <FillStyle index="1">
                          <BitmapFill bitmapPath="  Course Items-PL/ Blocks, Tiles &amp; Other Textures/ Rocks &amp; Blocks (Tiled)/BluerockMosaic" bitmapIsClipped="false">
                            <matrix>
                              <Matrix a="20" d="10.3805541992188" tx="-2616.7" ty="-790.5"/>
                            </matrix>
                          </BitmapFill>
                        </FillStyle>
                      </fills>
                      <strokes>
                        <StrokeStyle index="1">
                          <SolidStroke scaleMode="normal">
                            <fill>
                              <SolidColor/>
                            </fill>
                          </SolidStroke>
                        </StrokeStyle>
                      </strokes>
                      <edges>
                        <Edge fillStyle1="1" strokeStyle="1" edges="!-51445 -15773|-50724 -15274!-50724 -15274|-53130 -15274!-53130 -15274|-52604 -15773!-52604 -15773|-52244 -15773!-52244 -15773|-52244 -15634!-52244 -15634|-51784 -15634!-51784 -15634|-51784 -15773!-51784 -15773|-51445 -15773"/>
                      </edges>
                    </DOMShape>
                  </members>
                </DOMGroup>
                <DOMSymbolInstance libraryItemName="  Course Items-PL/ In-course Items/ Transportation/ Cannon/Cannon (main) Clip">
                  <matrix>
                    <Matrix tx="-2690.2" ty="-767.65"/>
                  </matrix>
                  <transformationPoint>
                    <Point/>
                  </transformationPoint>
                  <Actionscript>
                    <script><![CDATA[onClipEvent (load) {
	Xpower = 15;
	Ypower = 35;
	cannonsetup = true;
}
]]></script>
                  </Actionscript>
                </DOMSymbolInstance>
                <DOMSymbolInstance libraryItemName="  Course Items-PL/ In-course Items/ Collectables/ Coin: Yellow Folder/Gold Coin Code">
                  <matrix>
                    <Matrix tx="-1423.2" ty="-1113.6"/>
                  </matrix>
                  <transformationPoint>
                    <Point/>
                  </transformationPoint>
                </DOMSymbolInstance>
                <DOMSymbolInstance libraryItemName="  Course Items-PL/ In-course Items/ Collectables/ Coin: Yellow Folder/Gold Coin Code">
                  <matrix>
                    <Matrix tx="-1373.2" ty="-1113.6"/>
                  </matrix>
                  <transformationPoint>
                    <Point/>
                  </transformationPoint>
                </DOMSymbolInstance>
                <DOMSymbolInstance libraryItemName="  Course Items-PL/ In-course Items/ Collectables/ Coin: Yellow Folder/Gold Coin Code">
                  <matrix>
                    <Matrix tx="-1323.2" ty="-1113.6"/>
                  </matrix>
                  <transformationPoint>
                    <Point/>
                  </transformationPoint>
                </DOMSymbolInstance>
                <DOMSymbolInstance libraryItemName="  Course Items-PL/ In-course Items/ Collectables/ Coin: Yellow Folder/Gold Coin Code">
                  <matrix>
                    <Matrix tx="-1273.2" ty="-1113.6"/>
                  </matrix>
                  <transformationPoint>
                    <Point/>
                  </transformationPoint>
                </DOMSymbolInstance>
                <DOMSymbolInstance libraryItemName="  Course Items-PL/ In-course Items/ Collectables/ Coin: Yellow Folder/Gold Coin Code">
                  <matrix>
                    <Matrix tx="-152.45" ty="-28.05"/>
                  </matrix>
                  <transformationPoint>
                    <Point/>
                  </transformationPoint>
                </DOMSymbolInstance>
                <DOMSymbolInstance libraryItemName="  Course Items-PL/ In-course Items/ Collectables/ Coin: Yellow Folder/Gold Coin Code">
                  <matrix>
                    <Matrix tx="-612.8" ty="-33.05"/>
                  </matrix>
                  <transformationPoint>
                    <Point/>
                  </transformationPoint>
                </DOMSymbolInstance>
                <DOMSymbolInstance libraryItemName="  Course Items-PL/ In-course Items/ Collectables/ Coin: Yellow Folder/Gold Coin Code">
                  <matrix>
                    <Matrix tx="-582.8" ty="-33.05"/>
                  </matrix>
                  <transformationPoint>
                    <Point/>
                  </transformationPoint>
                </DOMSymbolInstance>
                <DOMSymbolInstance libraryItemName="  Course Items-PL/ In-course Items/ Collectables/ Coin: Yellow Folder/Gold Coin Code">
                  <matrix>
                    <Matrix tx="-757.1" ty="-2.5"/>
                  </matrix>
                  <transformationPoint>
                    <Point/>
                  </transformationPoint>
                </DOMSymbolInstance>
                <DOMSymbolInstance libraryItemName="  Course Items-PL/ In-course Items/ Collectables/ Coin: Yellow Folder/Gold Coin Code">
                  <matrix>
                    <Matrix tx="-727.1" ty="-2.5"/>
                  </matrix>
                  <transformationPoint>
                    <Point/>
                  </transformationPoint>
                </DOMSymbolInstance>
                <DOMSymbolInstance libraryItemName="  Course Items-PL/ In-course Items/ Collectables/ Coin: Yellow Folder/Gold Coin Code">
                  <matrix>
                    <Matrix tx="-1010.65" ty="-19.45"/>
                  </matrix>
                  <transformationPoint>
                    <Point/>
                  </transformationPoint>
                </DOMSymbolInstance>
                <DOMSymbolInstance libraryItemName="  Course Items-PL/ In-course Items/ Collectables/ Coin: Yellow Folder/Gold Coin Code">
                  <matrix>
                    <Matrix tx="-957" ty="-19.75"/>
                  </matrix>
                  <transformationPoint>
                    <Point/>
                  </transformationPoint>
                </DOMSymbolInstance>
                <DOMSymbolInstance libraryItemName="  Course Items-PL/ In-course Items/ Collectables/ Coin: Yellow Folder/Gold Coin Code">
                  <matrix>
                    <Matrix tx="-901" ty="-21.45"/>
                  </matrix>
                  <transformationPoint>
                    <Point/>
                  </transformationPoint>
                </DOMSymbolInstance>
                <DOMSymbolInstance libraryItemName="  Course Items-PL/ In-course Items/ Collectables/ Coin: Yellow Folder/Gold Coin Code">
                  <matrix>
                    <Matrix tx="-1160.4" ty="-12.45"/>
                  </matrix>
                  <transformationPoint>
                    <Point/>
                  </transformationPoint>
                </DOMSymbolInstance>
                <DOMSymbolInstance libraryItemName="  Course Items-PL/ In-course Items/ Collectables/ Coin: Yellow Folder/Gold Coin Code">
                  <matrix>
                    <Matrix tx="-1130.4" ty="-12.45"/>
                  </matrix>
                  <transformationPoint>
                    <Point/>
                  </transformationPoint>
                </DOMSymbolInstance>
                <DOMSymbolInstance libraryItemName="  Course Items-PL/ In-course Items/ Collectables/ Coin: Yellow Folder/Gold Coin Code">
                  <matrix>
                    <Matrix tx="-1404.25" ty="4.5"/>
                  </matrix>
                  <transformationPoint>
                    <Point/>
                  </transformationPoint>
                </DOMSymbolInstance>
                <DOMSymbolInstance libraryItemName="  Course Items-PL/ In-course Items/ Collectables/ Coin: Yellow Folder/Gold Coin Code">
                  <matrix>
                    <Matrix tx="-1294.6" ty="2.5"/>
                  </matrix>
                  <transformationPoint>
                    <Point/>
                  </transformationPoint>
                </DOMSymbolInstance>
                <DOMSymbolInstance libraryItemName="  Course Items-PL/ In-course Items/ Collectables/ Coin: Yellow Folder/Gold Coin Code">
                  <matrix>
                    <Matrix tx="-1511.4" ty="-1.45"/>
                  </matrix>
                  <transformationPoint>
                    <Point/>
                  </transformationPoint>
                </DOMSymbolInstance>
                <DOMSymbolInstance libraryItemName="  Course Items-PL/ In-course Items/ Collectables/ Coin: Yellow Folder/Gold Coin Code">
                  <matrix>
                    <Matrix tx="-1471.4" ty="-1.45"/>
                  </matrix>
                  <transformationPoint>
                    <Point/>
                  </transformationPoint>
                </DOMSymbolInstance>
                <DOMSymbolInstance libraryItemName="  Course Items-PL/ In-course Items/ Collectables/ Coin: Yellow Folder/Gold Coin Code">
                  <matrix>
                    <Matrix tx="-1623.4" ty="-19.45"/>
                  </matrix>
                  <transformationPoint>
                    <Point/>
                  </transformationPoint>
                </DOMSymbolInstance>
                <DOMSymbolInstance libraryItemName="  Course Items-PL/ In-course Items/ Collectables/ Coin: Yellow Folder/Gold Coin Code">
                  <matrix>
                    <Matrix tx="-1593.4" ty="-19.45"/>
                  </matrix>
                  <transformationPoint>
                    <Point/>
                  </transformationPoint>
                </DOMSymbolInstance>
                <DOMSymbolInstance libraryItemName="  Course Items-PL/ In-course Items/ Collectables/ Coin: Yellow Folder/Gold Coin Code">
                  <matrix>
                    <Matrix tx="-1731.4" ty="-11.5"/>
                  </matrix>
                  <transformationPoint>
                    <Point/>
                  </transformationPoint>
                </DOMSymbolInstance>
                <DOMSymbolInstance libraryItemName="  Course Items-PL/ In-course Items/ Collectables/ Coin: Yellow Folder/Gold Coin Code">
                  <matrix>
                    <Matrix tx="-1691.4" ty="-11.5"/>
                  </matrix>
                  <transformationPoint>
                    <Point/>
                  </transformationPoint>
                </DOMSymbolInstance>
                <DOMSymbolInstance libraryItemName="   Enemies/Normal/ G-Z/ Koopa/Koopa Code">
                  <matrix>
                    <Matrix tx="-2256.4" ty="-407"/>
                  </matrix>
                  <transformationPoint>
                    <Point/>
                  </transformationPoint>
                  <Actionscript>
                    <script><![CDATA[onClipEvent (load) {
	State = "Flying";
}
]]></script>
                  </Actionscript>
                </DOMSymbolInstance>
                <DOMSymbolInstance libraryItemName="   Enemies/Normal/ G-Z/ Koopa/Koopa Code">
                  <matrix>
                    <Matrix tx="-1655.4" ty="-239"/>
                  </matrix>
                  <transformationPoint>
                    <Point/>
                  </transformationPoint>
                  <Actionscript>
                    <script><![CDATA[onClipEvent (load) {
	State = "Flying";
}
]]></script>
                  </Actionscript>
                </DOMSymbolInstance>
                <DOMSymbolInstance libraryItemName="   Enemies/Normal/ G-Z/ Koopa/Koopa Code">
                  <matrix>
                    <Matrix tx="-664.15" ty="8.55"/>
                  </matrix>
                  <transformationPoint>
                    <Point/>
                  </transformationPoint>
                  <Actionscript>
                    <script><![CDATA[onClipEvent (load) {
	State = "Flying";
}
]]></script>
                  </Actionscript>
                </DOMSymbolInstance>
                <DOMSymbolInstance libraryItemName="   Enemies/Normal/ G-Z/ Koopa/Koopa Code">
                  <matrix>
                    <Matrix tx="-2432.2" ty="-807.85"/>
                  </matrix>
                  <transformationPoint>
                    <Point/>
                  </transformationPoint>
                  <Actionscript>
                    <script><![CDATA[onClipEvent (load) {
	State = "Flying";
}
]]></script>
                  </Actionscript>
                </DOMSymbolInstance>
                <DOMSymbolInstance libraryItemName="   Enemies/Normal/ G-Z/ Koopa/Koopa Code">
                  <matrix>
                    <Matrix tx="-1220.4" ty="25.2"/>
                  </matrix>
                  <transformationPoint>
                    <Point/>
                  </transformationPoint>
                  <Actionscript>
                    <script><![CDATA[onClipEvent (load) {
	State = "Flying";
}
]]></script>
                  </Actionscript>
                </DOMSymbolInstance>
                <DOMSymbolInstance libraryItemName="   Enemies/Normal/ G-Z/ Koopa/Koopa Code">
                  <matrix>
                    <Matrix tx="-1996.35" ty="-618"/>
                  </matrix>
                  <transformationPoint>
                    <Point/>
                  </transformationPoint>
                  <Actionscript>
                    <script><![CDATA[onClipEvent (load) {
	State = "Flying";
}
]]></script>
                  </Actionscript>
                </DOMSymbolInstance>
                <DOMSymbolInstance libraryItemName="   Enemies/Normal/ G-Z/ Shy-Guy/Shy Guy Code">
                  <matrix>
                    <Matrix tx="-1684.4" ty="-124.05"/>
                  </matrix>
                  <transformationPoint>
                    <Point/>
                  </transformationPoint>
                  <Actionscript>
                    <script><![CDATA[onClipEvent (load) {
	State = "Flying";
}
]]></script>
                  </Actionscript>
                </DOMSymbolInstance>
                <DOMSymbolInstance libraryItemName="   Enemies/Normal/ G-Z/ Shy-Guy/Shy Guy Code">
                  <matrix>
                    <Matrix tx="-717.45" ty="-184.5"/>
                  </matrix>
                  <transformationPoint>
                    <Point/>
                  </transformationPoint>
                  <Actionscript>
                    <script><![CDATA[onClipEvent (load) {
	State = "Flying";
}
]]></script>
                  </Actionscript>
                </DOMSymbolInstance>
                <DOMSymbolInstance libraryItemName="   Enemies/Normal/ G-Z/ Shy-Guy/Shy Guy Code">
                  <matrix>
                    <Matrix tx="-2289.4" ty="-1049.2"/>
                  </matrix>
                  <transformationPoint>
                    <Point/>
                  </transformationPoint>
                  <Actionscript>
                    <script><![CDATA[onClipEvent (load) {
	State = "Flying";
}
]]></script>
                  </Actionscript>
                </DOMSymbolInstance>
                <DOMSymbolInstance libraryItemName="   Enemies/Normal/ G-Z/ Shy-Guy/Shy Guy Code">
                  <matrix>
                    <Matrix tx="-2517.9" ty="-1178"/>
                  </matrix>
                  <transformationPoint>
                    <Point/>
                  </transformationPoint>
                  <Actionscript>
                    <script><![CDATA[onClipEvent (load) {
	State = "Flying";
}
]]></script>
                  </Actionscript>
                </DOMSymbolInstance>
                <DOMSymbolInstance libraryItemName="  Course Items-PL/ In-course Items/ Collectables/ Coin: Star Folder/Star Coin Code">
                  <matrix>
                    <Matrix tx="-2447.25" ty="-1164.5"/>
                  </matrix>
                  <transformationPoint>
                    <Point x="0.5" y="-0.05"/>
                  </transformationPoint>
                  <Actionscript>
                    <script><![CDATA[onClipEvent (load) {
	StarCoinNum = 2;
}
]]></script>
                  </Actionscript>
                </DOMSymbolInstance>
                <DOMSymbolInstance libraryItemName="  Course Items-PL/ In-course Items/ Collectables/ Water Bottle/Small Water Bottle Clip">
                  <matrix>
                    <Matrix tx="-1353.9" ty="7.8"/>
                  </matrix>
                  <transformationPoint>
                    <Point x="-0.05" y="7.4"/>
                  </transformationPoint>
                </DOMSymbolInstance>
                <DOMSymbolInstance libraryItemName="      Char/  Fludd CLIPS/Squirt Nozzle Box Clip">
                  <matrix>
                    <Matrix tx="-361" ty="-8.45"/>
                  </matrix>
                  <transformationPoint>
                    <Point/>
                  </transformationPoint>
                </DOMSymbolInstance>
                <DOMSymbolInstance libraryItemName="  Course Items-PL/ In-course Items/ Collectables/ Coin: Yellow Folder/Gold Coin Code">
                  <matrix>
                    <Matrix tx="-263.55" ty="-13.5"/>
                  </matrix>
                  <transformationPoint>
                    <Point/>
                  </transformationPoint>
                </DOMSymbolInstance>
                <DOMSymbolInstance libraryItemName="  Course Items-PL/ In-course Items/ Collectables/ Coin: Yellow Folder/Gold Coin Code">
                  <matrix>
                    <Matrix tx="-461.2" ty="-11.5"/>
                  </matrix>
                  <transformationPoint>
                    <Point/>
                  </transformationPoint>
                </DOMSymbolInstance>
                <DOMSymbolInstance libraryItemName="  Course Items-PL/ Various Platforms/ Coded Wooden PL/Tipping Log">
                  <matrix>
                    <Matrix tx="-1976.4" ty="-15.05"/>
                  </matrix>
                  <transformationPoint>
                    <Point y="-6"/>
                  </transformationPoint>
                  <Actionscript>
                    <script><![CDATA[onClipEvent (load) {
	scale = 3;
}
]]></script>
                  </Actionscript>
                </DOMSymbolInstance>
                <DOMSymbolInstance libraryItemName="  Course Items-PL/ Various Platforms/ Common Coded PL/ Green PL/Touch-Move Green Platforms">
                  <matrix>
                    <Matrix tx="-2219.35" ty="-218"/>
                  </matrix>
                  <transformationPoint>
                    <Point/>
                  </transformationPoint>
                  <Actionscript>
                    <script><![CDATA[onClipEvent (load) {
	DirectionX = "Right";
	DirectionY = "Up";
	distanceX = 65;
	distanceY = 65;
	accelX = 0.5;
	accelY = 0.5;
	speedX = 3;
	speedY = 3;
	//
	disapearcount = 60;
}
]]></script>
                  </Actionscript>
                </DOMSymbolInstance>
                <DOMSymbolInstance libraryItemName="  Course Items-PL/ In-course Items/ Collectables/ Power-Ups/Rainbow Star">
                  <matrix>
                    <Matrix tx="-2607.3" ty="-808.15"/>
                  </matrix>
                  <transformationPoint>
                    <Point/>
                  </transformationPoint>
                  <Actionscript>
                    <script><![CDATA[onClipEvent (load) {
	starfunction = function () {
		_root.StartNewMusicAndIntroNoVar("WingCap - Intro", "WingCap - Repeat");
		_root.PowerTimer = 32*45;
		_root.WingCap = true;
	};
}
]]></script>
                  </Actionscript>
                  <filters>
                    <AdjustColorFilter brightness="45" saturation="-78"/>
                    <BevelFilter blurX="2" blurY="2" distance="2" shadowColor="#666666"/>
                    <GlowFilter color="#FFFFFF"/>
                  </filters>
                </DOMSymbolInstance>
                <DOMSymbolInstance libraryItemName="  Course Items-PL/ Decoration/ Signs &amp; Fences/ Coded Sign/Coded Sign">
                  <matrix>
                    <Matrix tx="-2548.75" ty="-761.25"/>
                  </matrix>
                  <transformationPoint>
                    <Point/>
                  </transformationPoint>
                  <Actionscript>
                    <script><![CDATA[onClipEvent (load) {
	picture = true;
	signmessage = "wing";
}
]]></script>
                  </Actionscript>
                </DOMSymbolInstance>
                <DOMSymbolInstance libraryItemName="   Enemies/Normal/ G-Z/ Koopa/Koopa Code">
                  <matrix>
                    <Matrix tx="-1996.35" ty="-1189.6"/>
                  </matrix>
                  <transformationPoint>
                    <Point/>
                  </transformationPoint>
                  <Actionscript>
                    <script><![CDATA[onClipEvent (load) {
	State = "Flying";
}
]]></script>
                  </Actionscript>
                </DOMSymbolInstance>
                <DOMSymbolInstance libraryItemName="  Course Items-PL/ In-course Items/ Collectables/ Coin: Yellow Folder/Gold Coin Code">
                  <matrix>
                    <Matrix tx="-2384.55" ty="-1164.5"/>
                  </matrix>
                  <transformationPoint>
                    <Point/>
                  </transformationPoint>
                </DOMSymbolInstance>
                <DOMSymbolInstance libraryItemName="  Course Items-PL/ In-course Items/ Collectables/ Coin: Yellow Folder/Gold Coin Code">
                  <matrix>
                    <Matrix tx="-2334.55" ty="-1164.5"/>
                  </matrix>
                  <transformationPoint>
                    <Point/>
                  </transformationPoint>
                </DOMSymbolInstance>
                <DOMSymbolInstance libraryItemName="  Course Items-PL/ In-course Items/ Collectables/ Coin: Yellow Folder/Gold Coin Code">
                  <matrix>
                    <Matrix tx="-2284.55" ty="-1164.5"/>
                  </matrix>
                  <transformationPoint>
                    <Point/>
                  </transformationPoint>
                </DOMSymbolInstance>
                <DOMSymbolInstance libraryItemName="  Course Items-PL/ In-course Items/ Collectables/ Coin: Yellow Folder/Gold Coin Code">
                  <matrix>
                    <Matrix tx="-2234.55" ty="-1164.5"/>
                  </matrix>
                  <transformationPoint>
                    <Point/>
                  </transformationPoint>
                </DOMSymbolInstance>
                <DOMSymbolInstance libraryItemName="  Course Items-PL/ In-course Items/ Collectables/ Coin: Yellow Folder/Gold Coin Code">
                  <matrix>
                    <Matrix tx="-2184.55" ty="-1164.5"/>
                  </matrix>
                  <transformationPoint>
                    <Point/>
                  </transformationPoint>
                </DOMSymbolInstance>
                <DOMSymbolInstance libraryItemName="  Course Items-PL/ In-course Items/ Collectables/ Coin: Yellow Folder/Gold Coin Code">
                  <matrix>
                    <Matrix tx="-2134.55" ty="-1164.5"/>
                  </matrix>
                  <transformationPoint>
                    <Point/>
                  </transformationPoint>
                </DOMSymbolInstance>
                <DOMSymbolInstance libraryItemName="  Course Items-PL/ In-course Items/ Collectables/ Coin: Yellow Folder/Gold Coin Code">
                  <matrix>
                    <Matrix tx="-2084.55" ty="-1164.5"/>
                  </matrix>
                  <transformationPoint>
                    <Point/>
                  </transformationPoint>
                </DOMSymbolInstance>
                <DOMSymbolInstance libraryItemName="  Course Items-PL/ In-course Items/ Collectables/ Coin: Yellow Folder/Gold Coin Code">
                  <matrix>
                    <Matrix tx="-2034.55" ty="-1164.5"/>
                  </matrix>
                  <transformationPoint>
                    <Point/>
                  </transformationPoint>
                </DOMSymbolInstance>
                <DOMSymbolInstance libraryItemName="  Course Items-PL/ In-course Items/ Collectables/ Coin: Yellow Folder/Gold Coin Code">
                  <matrix>
                    <Matrix tx="-1984.55" ty="-1164.5"/>
                  </matrix>
                  <transformationPoint>
                    <Point/>
                  </transformationPoint>
                </DOMSymbolInstance>
                <DOMSymbolInstance libraryItemName="  Course Items-PL/ In-course Items/ Collectables/ Coin: Yellow Folder/Gold Coin Code">
                  <matrix>
                    <Matrix tx="-1934.55" ty="-1164.5"/>
                  </matrix>
                  <transformationPoint>
                    <Point/>
                  </transformationPoint>
                </DOMSymbolInstance>
                <DOMSymbolInstance libraryItemName="  Course Items-PL/ In-course Items/ Collectables/ Coin: Yellow Folder/Gold Coin Code">
                  <matrix>
                    <Matrix tx="-1884.55" ty="-1164.5"/>
                  </matrix>
                  <transformationPoint>
                    <Point/>
                  </transformationPoint>
                </DOMSymbolInstance>
                <DOMSymbolInstance libraryItemName="  Course Items-PL/ In-course Items/ Collectables/ Coin: Yellow Folder/Gold Coin Code">
                  <matrix>
                    <Matrix tx="-1834.55" ty="-1164.5"/>
                  </matrix>
                  <transformationPoint>
                    <Point/>
                  </transformationPoint>
                </DOMSymbolInstance>
                <DOMSymbolInstance libraryItemName="  Course Items-PL/ In-course Items/ Collectables/ Coin: Yellow Folder/Gold Coin Code">
                  <matrix>
                    <Matrix tx="-1784.55" ty="-1164.5"/>
                  </matrix>
                  <transformationPoint>
                    <Point/>
                  </transformationPoint>
                </DOMSymbolInstance>
                <DOMSymbolInstance libraryItemName="  Course Items-PL/ In-course Items/ Collectables/ Coin: Yellow Folder/Gold Coin Code">
                  <matrix>
                    <Matrix tx="-1734.55" ty="-1164.5"/>
                  </matrix>
                  <transformationPoint>
                    <Point/>
                  </transformationPoint>
                </DOMSymbolInstance>
                <DOMSymbolInstance libraryItemName="  Course Items-PL/ In-course Items/ Collectables/ Coin: Yellow Folder/Gold Coin Code">
                  <matrix>
                    <Matrix tx="-1684.55" ty="-1164.5"/>
                  </matrix>
                  <transformationPoint>
                    <Point/>
                  </transformationPoint>
                </DOMSymbolInstance>
                <DOMSymbolInstance libraryItemName="  Course Items-PL/ In-course Items/ Collectables/ Coin: Yellow Folder/Gold Coin Code">
                  <matrix>
                    <Matrix tx="-1634.55" ty="-1164.5"/>
                  </matrix>
                  <transformationPoint>
                    <Point/>
                  </transformationPoint>
                </DOMSymbolInstance>
                <DOMSymbolInstance libraryItemName="  Course Items-PL/ In-course Items/ Collectables/ Coin: Yellow Folder/Gold Coin Code">
                  <matrix>
                    <Matrix tx="-1584.55" ty="-1164.5"/>
                  </matrix>
                  <transformationPoint>
                    <Point/>
                  </transformationPoint>
                </DOMSymbolInstance>
                <DOMSymbolInstance libraryItemName="  Course Items-PL/ In-course Items/ Collectables/ Coin: Yellow Folder/Gold Coin Code">
                  <matrix>
                    <Matrix tx="-1534.55" ty="-1164.5"/>
                  </matrix>
                  <transformationPoint>
                    <Point/>
                  </transformationPoint>
                </DOMSymbolInstance>
                <DOMSymbolInstance libraryItemName="   Enemies/Normal/ G-Z/ Shy-Guy/Shy Guy Code">
                  <matrix>
                    <Matrix tx="-1746.4" ty="-1092.1"/>
                  </matrix>
                  <transformationPoint>
                    <Point/>
                  </transformationPoint>
                  <Actionscript>
                    <script><![CDATA[onClipEvent (load) {
	State = "Flying";
}
]]></script>
                  </Actionscript>
                </DOMSymbolInstance>
              </elements>
            </DOMFrame>
          </frames>
        </DOMLayer>
      </layers>
    </DOMTimeline>
  </timeline>
</DOMSymbolItem>