<DOMSymbolItem xmlns:xsi="http://www.w3.org/2001/XMLSchema-instance" xmlns="http://ns.adobe.com/xfl/2008/" name="  Course Items-PL/ Backgrounds/6-Hills+Ground Background " itemID="4737e3f1-00000e90" linkageExportForAS="true" linkageExportInFirstFrame="false" linkageIdentifier="GrassandHillsBG2" lastModified="1230056251">
  <timeline>
    <DOMTimeline name="6-Hills+Ground Background ">
      <layers>
        <DOMLayer name="Layer 3" color="#FFFF4F">
          <frames>
            <DOMFrame index="0" keyMode="9728">
              <elements>
                <DOMGroup>
                  <matrix>
                    <Matrix tx="-18.7" ty="140"/>
                  </matrix>
                  <members>
                    <DOMShape>
                      <matrix>
                        <Matrix tx="-18.7" ty="140"/>
                      </matrix>
                      <fills>
                        <FillStyle index="1">
                          <BitmapFill bitmapPath="  Course Items-PL/ Backgrounds/BG Hills Tree Repeat" bitmapIsClipped="false">
                            <matrix>
                              <Matrix a="20" d="20" tx="-4.05" ty="31.95"/>
                            </matrix>
                          </BitmapFill>
                        </FillStyle>
                      </fills>
                      <edges>
                        <Edge fillStyle1="1" edges="!11647 1399|-10899.5 1399!-10899.5 1399|-10899.5 639!-10899.5 639|11647 639!11647 639|11647 1399"/>
                      </edges>
                    </DOMShape>
                  </members>
                </DOMGroup>
              </elements>
            </DOMFrame>
          </frames>
        </DOMLayer>
        <DOMLayer name="Layer 4" color="#FF4FFF">
          <frames>
            <DOMFrame index="0" keyMode="9728">
              <elements>
                <DOMGroup>
                  <matrix>
                    <Matrix tx="-21.45" ty="140"/>
                  </matrix>
                  <transformationPoint>
                    <Point x="62.9" y="103.8"/>
                  </transformationPoint>
                  <members>
                    <DOMShape>
                      <matrix>
                        <Matrix tx="-21.45" ty="140"/>
                      </matrix>
                      <transformationPoint>
                        <Point x="62.9" y="103.8"/>
                      </transformationPoint>
                      <fills>
                        <FillStyle index="1">
                          <SolidColor color="#005300"/>
                        </FillStyle>
                        <FillStyle index="2">
                          <LinearGradient>
                            <matrix>
                              <Matrix a="0" b="-0.019317626953125" c="0.16033935546875" d="0" tx="68.3" ty="82.1"/>
                            </matrix>
                            <GradientEntry color="#305820" ratio="0"/>
                            <GradientEntry color="#346028" ratio="1"/>
                          </LinearGradient>
                        </FillStyle>
                        <FillStyle index="3">
                          <LinearGradient>
                            <matrix>
                              <Matrix a="0" b="-0.0114593505859375" c="0.10986328125" d="0" tx="69.2" ty="106.5"/>
                            </matrix>
                            <GradientEntry color="#005300" ratio="0"/>
                            <GradientEntry color="#306028" ratio="0.345098039215686"/>
                            <GradientEntry color="#035402" ratio="0.619607843137255"/>
                            <GradientEntry color="#305820" ratio="1"/>
                          </LinearGradient>
                        </FillStyle>
                        <FillStyle index="4">
                          <LinearGradient>
                            <matrix>
                              <Matrix a="0" b="-0.019317626953125" c="0.334121704101563" d="0" tx="557.45" ty="82.1"/>
                            </matrix>
                            <GradientEntry color="#305820" ratio="0"/>
                            <GradientEntry color="#346028" ratio="1"/>
                          </LinearGradient>
                        </FillStyle>
                        <FillStyle index="5">
                          <LinearGradient>
                            <matrix>
                              <Matrix a="0" b="-0.0114593505859375" c="0.22894287109375" d="0" tx="559.3" ty="106.5"/>
                            </matrix>
                            <GradientEntry color="#005300" ratio="0"/>
                            <GradientEntry color="#306028" ratio="0.345098039215686"/>
                            <GradientEntry color="#035402" ratio="0.619607843137255"/>
                            <GradientEntry color="#305820" ratio="1"/>
                          </LinearGradient>
                        </FillStyle>
                      </fills>
                      <edges>
                        <Edge fillStyle0="2" edges="!11708.5 1931.5|11708.5 1352!11708.5 1352|-7621 1352"/>
                        <Edge fillStyle0="2" fillStyle1="4" edges="!-7621 1352|-7621 1931.5"/>
                        <Edge fillStyle0="2" fillStyle1="3" edges="!-7621 1931.5|11708.5 1931.5"/>
                        <Edge fillStyle1="1" edges="!11708.5 2328.5|11708.5 2800.5!11708.5 2800.5|-10851 2800.5!-10851 2800.5|-10851 2328.5"/>
                        <Edge fillStyle1="5" edges="!-10851 2328.5|-10851 1931.5"/>
                        <Edge fillStyle1="4" edges="!-10851 1931.5|-10851 1352!-10851 1352|-7621 1352"/>
                        <Edge fillStyle1="3" edges="!11708.5 1931.5|11708.5 2328.5"/>
                        <Edge fillStyle0="5" fillStyle1="3" edges="!-7621 2328.5|-7621 1931.5"/>
                        <Edge fillStyle0="5" fillStyle1="4" edges="!-7621 1931.5|-10851 1931.5"/>
                        <Edge fillStyle0="5" fillStyle1="1" edges="!-10851 2328.5|-7621 2328.5"/>
                        <Edge fillStyle0="3" fillStyle1="1" edges="!-7621 2328.5|11708.5 2328.5"/>
                      </edges>
                    </DOMShape>
                  </members>
                </DOMGroup>
              </elements>
            </DOMFrame>
          </frames>
        </DOMLayer>
        <DOMLayer name="Layer 1" color="#4F80FF" current="true" isSelected="true">
          <frames>
            <DOMFrame index="0" keyMode="9728">
              <elements>
                <DOMSymbolInstance libraryItemName="  Course Items-PL/ Backgrounds/BG Hills Vectored">
                  <matrix>
                    <Matrix a="0.871719360351563" d="0.871719360351563" tx="-303.25" ty="110"/>
                  </matrix>
                  <transformationPoint>
                    <Point/>
                  </transformationPoint>
                </DOMSymbolInstance>
                <DOMSymbolInstance libraryItemName="  Course Items-PL/ Backgrounds/BG Hills Vectored">
                  <matrix>
                    <Matrix a="0.824676513671875" d="0.824676513671875" tx="-33.25" ty="118"/>
                  </matrix>
                  <transformationPoint>
                    <Point/>
                  </transformationPoint>
                </DOMSymbolInstance>
                <DOMSymbolInstance libraryItemName="  Course Items-PL/ Backgrounds/BG Hills Vectored">
                  <matrix>
                    <Matrix a="0.85888671875" d="0.85888671875" tx="206.75" ty="118"/>
                  </matrix>
                  <transformationPoint>
                    <Point/>
                  </transformationPoint>
                </DOMSymbolInstance>
              </elements>
            </DOMFrame>
          </frames>
        </DOMLayer>
      </layers>
    </DOMTimeline>
  </timeline>
</DOMSymbolItem>