<DOMSymbolItem xmlns:xsi="http://www.w3.org/2001/XMLSchema-instance" xmlns="http://ns.adobe.com/xfl/2008/" name="  Course Clips/ M - Mini Courses /M1-2 Ice" itemID="478293ad-00000d0d" linkageExportForAS="true" linkageExportInFirstFrame="false" linkageIdentifier="M1-2Ice" lastModified="1206164287">
  <timeline>
    <DOMTimeline name="M1-2 Ice">
      <layers>
        <DOMLayer name="Layer 2" color="#9933CC">
          <frames>
            <DOMFrame index="0" keyMode="9728">
              <Actionscript>
                <script><![CDATA[_visible = false]]></script>
              </Actionscript>
              <elements/>
            </DOMFrame>
          </frames>
        </DOMLayer>
        <DOMLayer name="Layer 1" color="#4FFF4F" current="true" isSelected="true">
          <frames>
            <DOMFrame index="0" keyMode="9728">
              <elements>
                <DOMShape>
                  <fills>
                    <FillStyle index="1">
                      <SolidColor color="#00FFFF"/>
                    </FillStyle>
                  </fills>
                  <edges>
                    <Edge fillStyle1="1" edges="!-29680 -6300|-28320 -2781!-28320 -2781|-28540 -2581!-28540 -2581|-30220 -6300!-30220 -6300|-29680 -6300"/>
                  </edges>
                </DOMShape>
              </elements>
            </DOMFrame>
          </frames>
        </DOMLayer>
      </layers>
    </DOMTimeline>
  </timeline>
</DOMSymbolItem>