<DOMSymbolItem xmlns:xsi="http://www.w3.org/2001/XMLSchema-instance" xmlns="http://ns.adobe.com/xfl/2008/" name="  Course Clips/ C - Castle/ Paintings/Bowser Picture Clip" itemID="46a37264-00000819" lastModified="1198556353">
  <timeline>
    <DOMTimeline name="Bowser Picture Clip">
      <layers>
        <DOMLayer name="Layer 1" color="#4FFF4F" current="true" isSelected="true">
          <frames>
            <DOMFrame index="0" keyMode="9728">
              <elements>
                <DOMBitmapInstance libraryItemName="  Course Clips/ C - Castle/ Paintings/Bowser Picture">
                  <matrix>
                    <Matrix a="0.666671752929688" d="0.68817138671875" tx="-32" ty="-32"/>
                  </matrix>
                </DOMBitmapInstance>
              </elements>
            </DOMFrame>
          </frames>
        </DOMLayer>
      </layers>
    </DOMTimeline>
  </timeline>
</DOMSymbolItem>