<DOMSymbolItem xmlns:xsi="http://www.w3.org/2001/XMLSchema-instance" xmlns="http://ns.adobe.com/xfl/2008/" name="      Char/  Mario CLIPS/Mairo Cinema Run" itemID="47374c3b-00000a8e" lastModified="1217802687" lastUniqueIdentifier="3">
  <timeline>
    <DOMTimeline name="Mairo Cinema Run">
      <layers>
        <DOMLayer name="Layer 3" color="#FFFF4F" current="true" isSelected="true">
          <frames>
            <DOMFrame index="0" duration="2" keyMode="9728">
              <elements>
                <DOMSymbolInstance libraryItemName="      Char/  Fludd CLIPS/Fludd Side Front">
                  <matrix>
                    <Matrix tx="0.45" ty="13.55"/>
                  </matrix>
                  <transformationPoint>
                    <Point/>
                  </transformationPoint>
                </DOMSymbolInstance>
              </elements>
            </DOMFrame>
            <DOMFrame index="2" duration="2" keyMode="9728">
              <elements>
                <DOMSymbolInstance libraryItemName="      Char/  Fludd CLIPS/Fludd Side Front">
                  <matrix>
                    <Matrix tx="1.45" ty="12.55"/>
                  </matrix>
                  <transformationPoint>
                    <Point/>
                  </transformationPoint>
                </DOMSymbolInstance>
              </elements>
            </DOMFrame>
            <DOMFrame index="4" duration="2" keyMode="9728">
              <elements>
                <DOMSymbolInstance libraryItemName="      Char/  Fludd CLIPS/Fludd Side Front">
                  <matrix>
                    <Matrix tx="0.45" ty="13.55"/>
                  </matrix>
                  <transformationPoint>
                    <Point/>
                  </transformationPoint>
                </DOMSymbolInstance>
              </elements>
            </DOMFrame>
            <DOMFrame index="6" duration="2" keyMode="9728">
              <elements>
                <DOMSymbolInstance libraryItemName="      Char/  Fludd CLIPS/Fludd Side Front">
                  <matrix>
                    <Matrix tx="1.45" ty="13.55"/>
                  </matrix>
                  <transformationPoint>
                    <Point/>
                  </transformationPoint>
                </DOMSymbolInstance>
              </elements>
            </DOMFrame>
            <DOMFrame index="8" duration="2" keyMode="9728">
              <elements>
                <DOMSymbolInstance libraryItemName="      Char/  Fludd CLIPS/Fludd Side Front">
                  <matrix>
                    <Matrix tx="0.45" ty="14.55"/>
                  </matrix>
                  <transformationPoint>
                    <Point/>
                  </transformationPoint>
                </DOMSymbolInstance>
              </elements>
            </DOMFrame>
            <DOMFrame index="10" duration="2" keyMode="9728">
              <elements>
                <DOMSymbolInstance libraryItemName="      Char/  Fludd CLIPS/Fludd Side Front">
                  <matrix>
                    <Matrix tx="2.45" ty="13.55"/>
                  </matrix>
                  <transformationPoint>
                    <Point/>
                  </transformationPoint>
                </DOMSymbolInstance>
              </elements>
            </DOMFrame>
            <DOMFrame index="12" duration="2" keyMode="9728">
              <elements>
                <DOMSymbolInstance libraryItemName="      Char/  Fludd CLIPS/Fludd Side Front">
                  <matrix>
                    <Matrix tx="1.45" ty="14.55"/>
                  </matrix>
                  <transformationPoint>
                    <Point/>
                  </transformationPoint>
                </DOMSymbolInstance>
              </elements>
            </DOMFrame>
            <DOMFrame index="14" duration="2" keyMode="9728">
              <elements>
                <DOMSymbolInstance libraryItemName="      Char/  Fludd CLIPS/Fludd Side Front">
                  <matrix>
                    <Matrix tx="-0.55" ty="14.55"/>
                  </matrix>
                  <transformationPoint>
                    <Point/>
                  </transformationPoint>
                </DOMSymbolInstance>
              </elements>
            </DOMFrame>
          </frames>
        </DOMLayer>
        <DOMLayer name="Layer 1" color="#4FFF4F">
          <frames>
            <DOMFrame index="0" duration="2" keyMode="9728">
              <elements>
                <DOMBitmapInstance libraryItemName="      Char/  BITS Mario/Mario Walk (none) - 1">
                  <matrix>
                    <Matrix tx="-7.65" ty="-10.65"/>
                  </matrix>
                </DOMBitmapInstance>
              </elements>
            </DOMFrame>
            <DOMFrame index="2" duration="2" keyMode="9728">
              <elements>
                <DOMBitmapInstance libraryItemName="      Char/  BITS Mario/Mario Walk (none) - 2">
                  <matrix>
                    <Matrix tx="-8.15" ty="-11.65"/>
                  </matrix>
                </DOMBitmapInstance>
              </elements>
            </DOMFrame>
            <DOMFrame index="4" duration="2" keyMode="9728">
              <elements>
                <DOMBitmapInstance libraryItemName="      Char/  BITS Mario/Mario Walk (none) - 3">
                  <matrix>
                    <Matrix tx="-7.65" ty="-10.65"/>
                  </matrix>
                </DOMBitmapInstance>
              </elements>
            </DOMFrame>
            <DOMFrame index="6" duration="2" keyMode="9728">
              <elements>
                <DOMBitmapInstance libraryItemName="      Char/  BITS Mario/Mario Walk (none) - 4">
                  <matrix>
                    <Matrix tx="-7.15" ty="-10.15"/>
                  </matrix>
                </DOMBitmapInstance>
              </elements>
            </DOMFrame>
            <DOMFrame index="8" duration="2" keyMode="9728">
              <elements>
                <DOMBitmapInstance libraryItemName="      Char/  BITS Mario/Mario Walk (none) - 5">
                  <matrix>
                    <Matrix tx="-8" ty="-8.65"/>
                  </matrix>
                </DOMBitmapInstance>
              </elements>
            </DOMFrame>
            <DOMFrame index="10" duration="2" keyMode="9728">
              <elements>
                <DOMBitmapInstance libraryItemName="      Char/  BITS Mario/Mario Walk (none) - 6">
                  <matrix>
                    <Matrix tx="-8.65" ty="-9.5"/>
                  </matrix>
                </DOMBitmapInstance>
              </elements>
            </DOMFrame>
            <DOMFrame index="12" duration="2" keyMode="9728">
              <elements>
                <DOMBitmapInstance libraryItemName="      Char/  BITS Mario/Mario Walk (none) - 7">
                  <matrix>
                    <Matrix tx="-8" ty="-8.65"/>
                  </matrix>
                </DOMBitmapInstance>
              </elements>
            </DOMFrame>
            <DOMFrame index="14" duration="2" keyMode="9728">
              <elements>
                <DOMBitmapInstance libraryItemName="      Char/  BITS Mario/Mario Walk (none) - 8">
                  <matrix>
                    <Matrix tx="-8.15" ty="-10.15"/>
                  </matrix>
                </DOMBitmapInstance>
              </elements>
            </DOMFrame>
          </frames>
        </DOMLayer>
        <DOMLayer name="Layer 2" color="#9933CC">
          <frames>
            <DOMFrame index="0" duration="2" keyMode="9728">
              <elements>
                <DOMSymbolInstance libraryItemName="      Char/  Fludd CLIPS/Fludd Side">
                  <matrix>
                    <Matrix tx="3.4" ty="-0.75"/>
                  </matrix>
                  <transformationPoint>
                    <Point y="-0.05"/>
                  </transformationPoint>
                </DOMSymbolInstance>
              </elements>
            </DOMFrame>
            <DOMFrame index="2" duration="2" keyMode="9728">
              <elements>
                <DOMSymbolInstance libraryItemName="      Char/  Fludd CLIPS/Fludd Side" selected="true">
                  <matrix>
                    <Matrix tx="4.4" ty="-1.75"/>
                  </matrix>
                  <transformationPoint>
                    <Point y="-0.05"/>
                  </transformationPoint>
                </DOMSymbolInstance>
              </elements>
            </DOMFrame>
            <DOMFrame index="4" duration="2" keyMode="9728">
              <elements>
                <DOMSymbolInstance libraryItemName="      Char/  Fludd CLIPS/Fludd Side" selected="true">
                  <matrix>
                    <Matrix tx="3.4" ty="-0.75"/>
                  </matrix>
                  <transformationPoint>
                    <Point y="-0.05"/>
                  </transformationPoint>
                </DOMSymbolInstance>
              </elements>
            </DOMFrame>
            <DOMFrame index="6" duration="2" keyMode="9728">
              <elements>
                <DOMSymbolInstance libraryItemName="      Char/  Fludd CLIPS/Fludd Side">
                  <matrix>
                    <Matrix tx="4.4" ty="-0.75"/>
                  </matrix>
                  <transformationPoint>
                    <Point y="-0.05"/>
                  </transformationPoint>
                </DOMSymbolInstance>
              </elements>
            </DOMFrame>
            <DOMFrame index="8" duration="2" keyMode="9728">
              <elements>
                <DOMSymbolInstance libraryItemName="      Char/  Fludd CLIPS/Fludd Side">
                  <matrix>
                    <Matrix tx="3.4" ty="0.25"/>
                  </matrix>
                  <transformationPoint>
                    <Point y="-0.05"/>
                  </transformationPoint>
                </DOMSymbolInstance>
              </elements>
            </DOMFrame>
            <DOMFrame index="10" duration="2" keyMode="9728">
              <elements>
                <DOMSymbolInstance libraryItemName="      Char/  Fludd CLIPS/Fludd Side">
                  <matrix>
                    <Matrix tx="5.4" ty="-0.75"/>
                  </matrix>
                  <transformationPoint>
                    <Point y="-0.05"/>
                  </transformationPoint>
                </DOMSymbolInstance>
              </elements>
            </DOMFrame>
            <DOMFrame index="12" duration="2" keyMode="9728">
              <elements>
                <DOMSymbolInstance libraryItemName="      Char/  Fludd CLIPS/Fludd Side">
                  <matrix>
                    <Matrix tx="4.4" ty="0.25"/>
                  </matrix>
                  <transformationPoint>
                    <Point y="-0.05"/>
                  </transformationPoint>
                </DOMSymbolInstance>
              </elements>
            </DOMFrame>
            <DOMFrame index="14" duration="2" keyMode="9728">
              <elements>
                <DOMSymbolInstance libraryItemName="      Char/  Fludd CLIPS/Fludd Side">
                  <matrix>
                    <Matrix tx="2.4" ty="0.25"/>
                  </matrix>
                  <transformationPoint>
                    <Point y="-0.05"/>
                  </transformationPoint>
                </DOMSymbolInstance>
              </elements>
            </DOMFrame>
          </frames>
        </DOMLayer>
      </layers>
    </DOMTimeline>
  </timeline>
</DOMSymbolItem>