<DOMSymbolItem xmlns:xsi="http://www.w3.org/2001/XMLSchema-instance" xmlns="http://ns.adobe.com/xfl/2008/" name="  Course Clips/4-8InvisGround" itemID="48ebe29a-00001138" lastModified="1223418594">
  <timeline>
    <DOMTimeline name="4-8InvisGround">
      <layers>
        <DOMLayer name="Layer 1" color="#4FFF4F" current="true" isSelected="true">
          <frames>
            <DOMFrame index="0" keyMode="9728">
              <elements>
                <DOMShape>
                  <fills>
                    <FillStyle index="1">
                      <SolidColor color="#00FF00"/>
                    </FillStyle>
                  </fills>
                  <edges>
                    <Edge fillStyle1="1" edges="!300 -1580|300 1540!300 1540|-300 1540!-300 1540|-300 -1580!-300 -1580|300 -1580!-37647 -1600|-37647 1520!-37647 1520|-38247 1520!-38247 1520|-38247 -1600!-38247 -1600|-37647 -1600"/>
                  </edges>
                </DOMShape>
              </elements>
            </DOMFrame>
          </frames>
        </DOMLayer>
      </layers>
    </DOMTimeline>
  </timeline>
</DOMSymbolItem>