<DOMSymbolItem xmlns:xsi="http://www.w3.org/2001/XMLSchema-instance" xmlns="http://ns.adobe.com/xfl/2008/" name="  Course Items-PL/ Various Platforms/ Common Coded PL/Rotating Block Plat Code" itemID="45d7535f-0000038c" linkageExportForAS="true" linkageExportInFirstFrame="false" linkageIdentifier="Rotating Block Plat Code" lastModified="1237074974">
  <timeline>
    <DOMTimeline name="Rotating Block Plat Code">
      <layers>
        <DOMLayer name="Layer 1" color="#4FFF4F" current="true" isSelected="true">
          <frames>
            <DOMFrame index="0" keyMode="9728">
              <elements>
                <DOMShape>
                  <fills>
                    <FillStyle index="1">
                      <SolidColor color="#00FF00"/>
                    </FillStyle>
                  </fills>
                  <edges>
                    <Edge fillStyle0="1" edges="!934.5 -959.5[#372.C3 #FFFC17.6A 790 -1000.5!790 -1000.5|-790.5 -1000.5!-790.5 -1000.5[#FFFC7C.A5 #FFFC17.6B -952 -944.5!-952 -944.5[#FFFC17.6A -891.8125 -1000.5 -790.5!-1000.5 -790.5|-1000.5 789.5!-1000.5 789.5[#FFFC17.6B #382.1B -944.5
 950.5!-944.5 950.5[-891.8125 #3E7.56 -790.5 999.5!-790.5 999.5|790 999.5!790 999.5[#376.AE #3E7.66 939 955!939 955[#3E7.AF #386.A9 999.5 789.5!999.5 789.5|999.5 -790.5!999.5 -790.5[#3E7.A1 #FFFC74.4C 934.5 -959.5"/>
                  </edges>
                </DOMShape>
              </elements>
            </DOMFrame>
          </frames>
        </DOMLayer>
      </layers>
    </DOMTimeline>
  </timeline>
</DOMSymbolItem>