<DOMSymbolItem xmlns:xsi="http://www.w3.org/2001/XMLSchema-instance" xmlns="http://ns.adobe.com/xfl/2008/" name="FX kAmek Sparkle effec tlcip" itemID="49656f77-00000f81" sourceFlashFilepath="F:\Super Mario 63\New computer\Kamek Sparkle Effect.fla" sourceLibraryItemHRef="FX kAmek Sparkle effec tlcip" sourceLastModified="1231472938" lastModified="1231472938" sourceItemID="49656f77-00000f81">
  <timeline>
    <DOMTimeline name="FX kAmek Sparkle effec tlcip">
      <layers>
        <DOMLayer name="Layer 3" color="#FFFF4F" current="true" isSelected="true" heightLiteral="15">
          <frames>
            <DOMFrame index="0" duration="20" keyMode="9728">
              <Actionscript>
                <script><![CDATA[if (re == undefined) {
	re == 1;
	gotoAndPlay(random(20));
}
]]></script>
              </Actionscript>
              <elements/>
            </DOMFrame>
          </frames>
        </DOMLayer>
        <DOMLayer name="Layer 2" color="#9933CC" heightLiteral="15">
          <frames>
            <DOMFrame index="0" duration="4" keyMode="9728">
              <elements>
                <DOMShape>
                  <fills>
                    <FillStyle index="1">
                      <SolidColor color="#FFFFFF" alpha="0.250980392156863"/>
                    </FillStyle>
                  </fills>
                  <edges>
                    <Edge fillStyle1="1" edges="!-28 -78[-28 -48 -60 -48!-60 -48[-91 -48 -90 -80!-90 -80[-90 -110 -60 -110!-60 -110[-31 -110 -28 -78"/>
                    <Edge cubics="!-60 -110(;-31,-110 -28,-81 -28,-78q-60 -110Q-31 -110q-28 -78);"/>
                    <Edge cubics="!-28 -78(;-28,-65 -40,-48 -60,-48q-28 -78Q-28 -67q-36 -58Q-46 -48q-60 -48);"/>
                    <Edge cubics="!-60 -48(;-91,-48 -90,-78 -90,-80q-60 -48Q-91 -48q-90 -80);"/>
                    <Edge cubics="!-90 -80(;-90,-93 -77,-110 -60,-110q-90 -80Q-90 -90q-81 -100Q-72 -110q-60 -110);"/>
                  </edges>
                </DOMShape>
              </elements>
            </DOMFrame>
            <DOMFrame index="4" duration="5" keyMode="9728">
              <elements>
                <DOMShape>
                  <fills>
                    <FillStyle index="1">
                      <SolidColor color="#FFFFFF" alpha="0.250980392156863"/>
                    </FillStyle>
                  </fills>
                  <edges>
                    <Edge fillStyle1="1" edges="!115 -73[115 -43 85 -43!85 -43[53 -43 53 -75!53 -75[53 -105 85 -105!85 -105[112 -105 115 -73"/>
                    <Edge cubics="!85 -105(;112,-105 115,-76 115,-73q85 -105Q112 -105q115 -73);"/>
                    <Edge cubics="!115 -73(;115,-60 104,-43 85,-43q115 -73Q115 -62q107 -53Q98 -43q85 -43);"/>
                    <Edge cubics="!85 -43(;53,-43 53,-73 53,-75q85 -43Q53 -43q53 -75);"/>
                    <Edge cubics="!53 -75(;53,-89 66,-105 85,-105q53 -75Q53 -86q62 -95Q71 -105q85 -105);"/>
                  </edges>
                </DOMShape>
              </elements>
            </DOMFrame>
            <DOMFrame index="9" duration="5" keyMode="9728">
              <elements>
                <DOMShape>
                  <fills>
                    <FillStyle index="1">
                      <SolidColor color="#FFFFFF" alpha="0.250980392156863"/>
                    </FillStyle>
                  </fills>
                  <edges>
                    <Edge fillStyle1="1" edges="!-38 90[-38 120 -70 120!-70 120[-100 120 -100 89!-100 89[-100 58 -70 58!-70 58[-41 58 -38 90"/>
                    <Edge cubics="!-70 58(;-41,58 -38,88 -38,90q-70 58Q-41 58q-38 90);"/>
                    <Edge cubics="!-38 90(;-38,104 -50,120 -70,120q-38 90Q-38 101q-46 110Q-56 120q-70 120);"/>
                    <Edge cubics="!-70 120(;-100,120 -100,91 -100,89q-70 120Q-100 120q-100 89);"/>
                    <Edge cubics="!-100 89(;-100,75 -87,58 -70,58q-100 89Q-100 78q-91 68Q-82 58q-70 58);"/>
                  </edges>
                </DOMShape>
              </elements>
            </DOMFrame>
            <DOMFrame index="14" duration="5" keyMode="9728">
              <elements>
                <DOMShape>
                  <fills>
                    <FillStyle index="1">
                      <SolidColor color="#FFFFFF" alpha="0.250980392156863"/>
                    </FillStyle>
                  </fills>
                  <edges>
                    <Edge fillStyle1="1" edges="!125 90[125 120 95 120!95 120[63 120 63 89!63 89[63 58 95 58!95 58[123 58 125 90"/>
                    <Edge cubics="!95 58(;123,58 125,88 125,90q95 58Q123 58q125 90);"/>
                    <Edge cubics="!125 90(;125,104 114,120 95,120q125 90Q125 101q117 110Q108 120q95 120);"/>
                    <Edge cubics="!95 120(;63,120 63,91 63,89q95 120Q63 120q63 89);"/>
                    <Edge cubics="!63 89(;63,75 76,58 95,58q63 89Q63 78q72 68Q82 58q95 58);"/>
                  </edges>
                </DOMShape>
              </elements>
            </DOMFrame>
            <DOMFrame index="19" keyMode="9728">
              <elements>
                <DOMShape>
                  <fills>
                    <FillStyle index="1">
                      <SolidColor color="#FFFFFF" alpha="0.250980392156863"/>
                    </FillStyle>
                  </fills>
                  <edges>
                    <Edge fillStyle1="1" edges="!5 30[-25 30 -25 0!-25 0[-25 -30 5 -30!5 -30[33 -30 35 0!35 0[35 30 5 30"/>
                    <Edge cubics="!5 -30(;33,-30 35,-1 35,0q5 -30Q33 -30q35 0);"/>
                    <Edge cubics="!35 0(;35,14 24,30 5,30q35 0Q35 11q27 20Q18 30q5 30);"/>
                    <Edge cubics="!5 30(;-25,30 -25,1 -25,0q5 30Q-25 30q-25 0);"/>
                    <Edge cubics="!-25 0(;-25,-14 -11,-30 5,-30q-25 0Q-25 -11q-16 -20Q-7 -30q5 -30);"/>
                  </edges>
                </DOMShape>
              </elements>
            </DOMFrame>
          </frames>
        </DOMLayer>
        <DOMLayer name="Layer 1" color="#4FFF4F" locked="true" heightLiteral="15">
          <frames>
            <DOMFrame index="0" duration="9" tweenType="shape" keyMode="17922">
              <MorphShape>
                <morphSegments>
                  <MorphSegment startPointA="-0.5859375, #FFFFFF.FF" startPointB="-0.5859375, #FFFFFF.FF" strokeIndex1="0" strokeIndex2="0" fillIndex1="0" fillIndex2="1">
                    <MorphCurves controlPointA="-0.3515625, -0.0625" anchorPointA="-0.1171875, #FFFFFF.E1" controlPointB="-0.3515625, -0.0625" anchorPointB="-0.1171875, #FFFFFF.E1" isLine="true"/>
                    <MorphCurves controlPointA="#FFFFFF.F1, #FFFFFF.A5" anchorPointA="0, -0.5859375" controlPointB="#FFFFFF.F1, #FFFFFF.A5" anchorPointB="0, -0.5859375" isLine="true"/>
                    <MorphCurves controlPointA="#0.0F, -0.3515625" anchorPointA="#0.1E, -0.1171875" controlPointB="#0.0F, -0.3515625" anchorPointB="#0.1E, -0.1171875" isLine="true"/>
                    <MorphCurves controlPointA="#0.5A, #FFFFFF.F1" anchorPointA="#0.96, 0" controlPointB="#0.5A, #FFFFFF.F1" anchorPointB="#0.96, 0" isLine="true"/>
                    <MorphCurves controlPointA="#0.5A, #0.0F" anchorPointA="#0.1E, #0.1E" controlPointB="#0.5A, #0.0F" anchorPointB="#0.1E, #0.1E" isLine="true"/>
                    <MorphCurves controlPointA="#0.0F, #0.5A" anchorPointA="0, #0.96" controlPointB="#0.0F, #0.5A" anchorPointB="0, #0.96" isLine="true"/>
                    <MorphCurves controlPointA="#FFFFFF.F1, #0.59" anchorPointA="-0.1171875, #0.1D" controlPointB="#FFFFFF.F1, #0.59" anchorPointB="-0.1171875, #0.1D" isLine="true"/>
                    <MorphCurves controlPointA="-0.3515625, #0.0E" anchorPointA="-0.5859375, #FFFFFF.FF" controlPointB="-0.3515625, #0.0E" anchorPointB="-0.5859375, #FFFFFF.FF" isLine="true"/>
                  </MorphSegment>
                </morphSegments>
                <morphHintsList/>
              </MorphShape>
              <elements>
                <DOMShape>
                  <fills>
                    <FillStyle index="1">
                      <SolidColor color="#FFFFFF"/>
                    </FillStyle>
                  </fills>
                  <edges>
                    <Edge fillStyle1="1" edges="!29.5 -30.5|149.5 -0.5!149.5 -0.5|29.5 29.5!29.5 29.5|-0.5 149.5!-0.5 149.5|-30.5 29!-30.5 29|-150.5 -1!-150.5 -1|-30.5 -31!-30.5 -31|0 -150.5!0 -150.5|29.5 -30.5"/>
                  </edges>
                </DOMShape>
              </elements>
            </DOMFrame>
            <DOMFrame index="9" duration="10" tweenType="shape" keyMode="17922">
              <MorphShape>
                <morphSegments>
                  <MorphSegment startPointA="-0.5859375, #FFFFFF.FF" startPointB="-0.5859375, #FFFFFF.FF" strokeIndex1="0" strokeIndex2="0" fillIndex1="0" fillIndex2="1">
                    <MorphCurves controlPointA="-0.3515625, -0.0625" anchorPointA="-0.1171875, #FFFFFF.E1" controlPointB="-0.3515625, -0.0625" anchorPointB="-0.1171875, #FFFFFF.E1" isLine="true"/>
                    <MorphCurves controlPointA="#FFFFFF.F1, #FFFFFF.A5" anchorPointA="0, -0.5859375" controlPointB="#FFFFFF.F1, #FFFFFF.A5" anchorPointB="0, -0.5859375" isLine="true"/>
                    <MorphCurves controlPointA="#0.0F, -0.3515625" anchorPointA="#0.1E, -0.1171875" controlPointB="#0.0F, -0.3515625" anchorPointB="#0.1E, -0.1171875" isLine="true"/>
                    <MorphCurves controlPointA="#0.5A, #FFFFFF.F1" anchorPointA="#0.96, 0" controlPointB="#0.5A, #FFFFFF.F1" anchorPointB="#0.96, 0" isLine="true"/>
                    <MorphCurves controlPointA="#0.5A, #0.0F" anchorPointA="#0.1E, #0.1E" controlPointB="#0.5A, #0.0F" anchorPointB="#0.1E, #0.1E" isLine="true"/>
                    <MorphCurves controlPointA="#0.0F, #0.5A" anchorPointA="0, #0.96" controlPointB="#0.0F, #0.5A" anchorPointB="0, #0.96" isLine="true"/>
                    <MorphCurves controlPointA="#FFFFFF.F1, #0.59" anchorPointA="-0.1171875, #0.1D" controlPointB="#FFFFFF.F1, #0.59" anchorPointB="-0.1171875, #0.1D" isLine="true"/>
                    <MorphCurves controlPointA="-0.3515625, #0.0E" anchorPointA="-0.5859375, #FFFFFF.FF" controlPointB="-0.3515625, #0.0E" anchorPointB="-0.5859375, #FFFFFF.FF" isLine="true"/>
                  </MorphSegment>
                </morphSegments>
                <morphHintsList/>
              </MorphShape>
              <elements>
                <DOMShape>
                  <fills>
                    <FillStyle index="1">
                      <SolidColor color="#A200DF"/>
                    </FillStyle>
                  </fills>
                  <edges>
                    <Edge fillStyle1="1" edges="!149.5 -0.5|29.5 29.5!29.5 29.5|-0.5 149.5!-0.5 149.5|-30.5 29!-30.5 29|-150.5 -1!-150.5 -1|-30.5 -31!-30.5 -31|0 -150.5!0 -150.5|29.5 -30.5!29.5 -30.5|149.5 -0.5"/>
                  </edges>
                </DOMShape>
              </elements>
            </DOMFrame>
            <DOMFrame index="19" keyMode="9728">
              <elements>
                <DOMShape>
                  <fills>
                    <FillStyle index="1">
                      <SolidColor color="#FFFFFF"/>
                    </FillStyle>
                  </fills>
                  <edges>
                    <Edge fillStyle1="1" edges="!149.5 -0.5|29.5 29.5!29.5 29.5|-0.5 149.5!-0.5 149.5|-30.5 29!-30.5 29|-150.5 -1!-150.5 -1|-30.5 -31!-30.5 -31|0 -150.5!0 -150.5|29.5 -30.5!29.5 -30.5|149.5 -0.5"/>
                  </edges>
                </DOMShape>
              </elements>
            </DOMFrame>
          </frames>
        </DOMLayer>
      </layers>
    </DOMTimeline>
  </timeline>
</DOMSymbolItem>